{
  "fct": {
    "typedData": {
      "types": {
        "EIP712Domain": [
          {
            "name": "name",
            "type": "string"
          },
          {
            "name": "version",
            "type": "string"
          },
          {
            "name": "chainId",
            "type": "uint256"
          },
          {
            "name": "verifyingContract",
            "type": "address"
          },
          {
            "name": "salt",
            "type": "bytes32"
          }
        ],
        "Meta": [
          {
            "name": "name",
            "type": "string"
          },
          {
            "name": "app",
            "type": "string"
          },
          {
            "name": "app_version",
            "type": "string"
          },
          {
            "name": "builder",
            "type": "string"
          },
          {
            "name": "builder_address",
            "type": "address"
          },
          {
            "name": "domain",
            "type": "string"
          }
        ],
        "Engine": [
          {
            "name": "selector",
            "type": "bytes4"
          },
          {
            "name": "version",
            "type": "bytes3"
          },
          {
            "name": "random_id",
            "type": "bytes3"
          },
          {
            "name": "eip712",
            "type": "bool"
          },
          {
            "name": "verifier",
            "type": "string"
          },
          {
            "name": "auth_enabled",
            "type": "bool"
          },
          {
            "name": "dry_run",
            "type": "bool"
          }
        ],
        "Limits": [
          {
            "name": "valid_from",
            "type": "uint40"
          },
          {
            "name": "expires_at",
            "type": "uint40"
          },
          {
            "name": "gas_price_limit",
            "type": "uint64"
          },
          {
            "name": "purgeable",
            "type": "bool"
          },
          {
            "name": "blockable",
            "type": "bool"
          }
        ],
        "transaction1": [
          {
            "name": "call",
            "type": "Call"
          },
          {
            "name": "key",
            "type": "bytes32"
          },
          {
            "name": "value",
            "type": "bytes"
          }
        ],
        "transaction2": [
          {
            "name": "call",
            "type": "Call"
          },
          {
            "name": "owner",
            "type": "address"
          },
          {
            "name": "key",
            "type": "bytes32"
          }
        ],
        "BatchMultiSigCall": [
          {
            "name": "meta",
            "type": "Meta"
          },
          {
            "name": "engine",
            "type": "Engine"
          },
          {
            "name": "limits",
            "type": "Limits"
          },
          {
            "name": "transaction_1",
            "type": "transaction1"
          },
          {
            "name": "transaction_2",
            "type": "transaction2"
          }
        ],
        "Call": [
          {
            "name": "call_index",
            "type": "uint16"
          },
          {
            "name": "payer_index",
            "type": "uint16"
          },
          {
            "name": "call_type",
            "type": "string"
          },
          {
            "name": "from",
            "type": "address"
          },
          {
            "name": "to",
            "type": "address"
          },
          {
            "name": "to_ens",
            "type": "string"
          },
          {
            "name": "value",
            "type": "uint256"
          },
          {
            "name": "gas_limit",
            "type": "uint32"
          },
          {
            "name": "permissions",
            "type": "uint16"
          },
          {
            "name": "validation",
            "type": "uint16"
          },
          {
            "name": "flow_control",
            "type": "string"
          },
          {
            "name": "returned_false_means_fail",
            "type": "bool"
          },
          {
            "name": "jump_on_success",
            "type": "uint16"
          },
          {
            "name": "jump_on_fail",
            "type": "uint16"
          },
          {
            "name": "method_interface",
            "type": "string"
          }
        ]
      },
      "primaryType": "BatchMultiSigCall",
      "domain": {
        "name": "FCT Controller",
        "version": "1",
        "chainId": 11155111,
        "verifyingContract": "0x1Bc4e8448E6B6703c7458C4Ee8361eB6c3015fD4",
        "salt": "0x01006e6774a58cfed2c900001bc4e8448e6b6703c7458c4ee8361eb6c3015fd4"
      },
      "message": {
        "meta": {
          "name": "Untitled-280025",
          "app": "",
          "app_version": "",
          "builder": "",
          "builder_address": "0x0000000000000000000000000000000000000000",
          "domain": ""
        },
        "engine": {
          "selector": "0x7d971612",
          "version": "0x020102",
          "random_id": "0x6ed107",
          "eip712": true,
          "verifier": "",
          "auth_enabled": false,
          "dry_run": false
        },
        "limits": {
          "valid_from": "1710245508",
          "expires_at": "1710246168",
          "gas_price_limit": "100000000000",
          "purgeable": false,
          "blockable": true
        },
        "transaction_1": {
          "call": {
            "call_index": 1,
            "payer_index": 1,
            "call_type": "action",
            "from": "0x3Df4553c3bdad34320B0677788b0c4955BDfe601",
            "to": "0xF71396c6F168Dc1c213AA9433cB0E7C1e4B07964",
            "to_ens": "",
            "value": "0",
            "gas_limit": "0",
            "permissions": 0,
            "validation": 0,
            "flow_control": "continue on success, revert on fail",
            "returned_false_means_fail": false,
            "jump_on_success": 0,
            "jump_on_fail": 0,
            "method_interface": "write_bytes(bytes32,bytes32)"
          },
          "key": "0x9c22ff5f21f0b81b113e63f7db6da94fedef11b2119b4088b89664fb9a3cb658",
          "value": "0x000000000000000000000000000000000000000000000000000000000000002000000000000000000000000000000000000000000000000000000000000000033132330000000000000000000000000000000000000000000000000000000000"
        },
        "transaction_2": {
          "call": {
            "call_index": 2,
            "payer_index": 2,
            "call_type": "view only",
            "from": "0x3Df4553c3bdad34320B0677788b0c4955BDfe601",
            "to": "0xF71396c6F168Dc1c213AA9433cB0E7C1e4B07964",
            "to_ens": "",
            "value": "0",
            "gas_limit": "0",
            "permissions": 0,
            "validation": 0,
            "flow_control": "stop on success, revert on fail",
            "returned_false_means_fail": false,
            "jump_on_success": 0,
            "jump_on_fail": 0,
            "method_interface": "read_bytes(address,bytes32)"
          },
          "owner": "0x3Df4553c3bdad34320B0677788b0c4955BDfe601",
          "key": "0x9c22ff5f21f0b81b113e63f7db6da94fedef11b2119b4088b89664fb9a3cb658"
        }
      }
    },
    "typeHash": "0xed689f3f536f80c28891cefbeccc84be8282794064fe53ba5b438980ed42ffbe",
    "sessionId": "0x6ed107000201020000000000000065f049180065f04684000000174876e8000c",
    "nameHash": "0x89f5b46d6ede4c61d3d602d80eba0ffc0639003a9116ce9d4a4bc09bf1a6aa4f",
    "appHash": "0xc5d2460186f7233c927e7db2dcc703c0e500b653ca82273b7bfad8045d85a470",
    "appVersionHash": "0xc5d2460186f7233c927e7db2dcc703c0e500b653ca82273b7bfad8045d85a470",
    "builderHash": "0xc5d2460186f7233c927e7db2dcc703c0e500b653ca82273b7bfad8045d85a470",
    "builderAddress": "0x0000000000000000000000000000000000000000",
    "domainHash": "0xc5d2460186f7233c927e7db2dcc703c0e500b653ca82273b7bfad8045d85a470",
    "verifierHash": "0xc5d2460186f7233c927e7db2dcc703c0e500b653ca82273b7bfad8045d85a470",
    "mcall": [
      {
        "typeHash": "0x81aca234ce6d0a15e0cbef029f0dc93d43a8e35a61693ecb24a82ecc9166f498",
        "ensHash": "0xc5d2460186f7233c927e7db2dcc703c0e500b653ca82273b7bfad8045d85a470",
        "functionSignature": "0xf3939727b235351826cdcdf90b8a67dfc3eb9e81974dbf53a85d93b152dac590",
        "value": "0",
        "callId": "0x0000000000000000000000000000000000000000000000000100010000000000",
        "from": "0x3Df4553c3bdad34320B0677788b0c4955BDfe601",
        "to": "0xF71396c6F168Dc1c213AA9433cB0E7C1e4B07964",
        "data": "0x4c56cd21e4213617574aa7cf2009104176f4d4ff5463b4a90ee854da95420e31190ee025879e75b326e40b7cb3690e61bf0108e92b2193dac73c757611e5636a",
        "types": [],
        "typedHashes": []
      },
      {
        "typeHash": "0x612bc26b1dea2bd524904a5c6fc152ffea53e8832b38ce87a9e980cc66dd042c",
        "ensHash": "0xc5d2460186f7233c927e7db2dcc703c0e500b653ca82273b7bfad8045d85a470",
        "functionSignature": "0xee0ac1b5c7ae2ed15399d7e205446706e7e3938f63e70ec593ecc0ff04c1f025",
        "value": "0",
        "callId": "0x0000000000000000000000000000000000000600000000000200020000000011",
        "from": "0x3Df4553c3bdad34320B0677788b0c4955BDfe601",
        "to": "0xF71396c6F168Dc1c213AA9433cB0E7C1e4B07964",
        "data": "0x0000000000000000000000003df4553c3bdad34320b0677788b0c4955bdfe6014c56cd21e4213617574aa7cf2009104176f4d4ff5463b4a90ee854da95420e31",
        "types": [],
        "typedHashes": []
      }
    ],
    "externalSigners": [],
    "signatures": [
      {
        "r": "0x2121abae083e50185168814b23b024349d32dbefd3cd2ac046ab88bc2c6660b9",
        "s": "0x353d3df754a176f0193d896fb8b9b0fd27e78cf3ff148048d6beb958df57871e",
        "_vs": "0x353d3df754a176f0193d896fb8b9b0fd27e78cf3ff148048d6beb958df57871e",
        "recoveryParam": 0,
        "v": 27,
        "yParityAndS": "0x353d3df754a176f0193d896fb8b9b0fd27e78cf3ff148048d6beb958df57871e",
        "compact": "0x2121abae083e50185168814b23b024349d32dbefd3cd2ac046ab88bc2c6660b9353d3df754a176f0193d896fb8b9b0fd27e78cf3ff148048d6beb958df57871e"
      }
    ],
    "computed": [],
    "validations": [],
    "variables": []
  }
}
